mrc/__init__.py
mrc/_version.py
mrc/py.typed
mrc/benchmarking/__init__.py
mrc/core/__init__.py
mrc/core/log_handler.py
mrc/tests/__init__.py
tmrc-23.7.0a0.dist-info/METADATA
tmrc-23.7.0a0.dist-info/WHEEL
tmrc-23.7.0a0.dist-info/top_level.txt
tmrc-23.7.0a0.dist-info/RECORD
