Metadata-Version: 2.1
Name: tmrc
Version: 23.7.0a0
Summary: tmrc
Author: NVIDIA Corporation
License: Apache
Classifier: Intended Audience :: Developers
Classifier: Programming Language :: Python
Classifier: Programming Language :: Python :: 3.10
